jupytercad_salome/__init__.py
jupytercad_salome/_version.py
jupytercad_salome/main.py
jupytercad_salome/salome_server/handler.py
jupytercad_salome/salome_server/mesh_builder.py
jupytercad_salome/schema/openapi.yaml
jupytercad_salome-2.0.0.data/data/etc/jupyter/jupyter_server_config.d/jupytercad_salome.json
jupytercad_salome-2.0.0.data/data/share/jupyter/labextensions/@jupytercad/jupytercad-salome/package.json
jupytercad_salome-2.0.0.data/data/share/jupyter/labextensions/@jupytercad/jupytercad-salome/static/657.ee82129e76948c6af0d4.js
jupytercad_salome-2.0.0.data/data/share/jupyter/labextensions/@jupytercad/jupytercad-salome/static/684.27e914a9d8a514145e21.js
jupytercad_salome-2.0.0.data/data/share/jupyter/labextensions/@jupytercad/jupytercad-salome/static/688.fbf9a2083872f3817a9b.js
jupytercad_salome-2.0.0.data/data/share/jupyter/labextensions/@jupytercad/jupytercad-salome/static/747.fc9166cbc0085e68707e.js
jupytercad_salome-2.0.0.data/data/share/jupyter/labextensions/@jupytercad/jupytercad-salome/static/remoteEntry.2385d0e780906d8d08bf.js
jupytercad_salome-2.0.0.data/data/share/jupyter/labextensions/@jupytercad/jupytercad-salome/static/style.js
jupytercad_salome-2.0.0.data/data/share/jupyter/labextensions/@jupytercad/jupytercad-salome/static/third-party-licenses.json
jupytercad_salome-2.0.0.data/data/share/jupyter/labextensions/@jupytercad/jupytercad-salome/install.json
jupytercad_salome-2.0.0.dist-info/METADATA
jupytercad_salome-2.0.0.dist-info/WHEEL
jupytercad_salome-2.0.0.dist-info/licenses/LICENSE
jupytercad_salome-2.0.0.dist-info/RECORD
